odoo/addons/shopfloor_delivery_shipment_mobile/README.rst
odoo/addons/shopfloor_delivery_shipment_mobile/__init__.py
odoo/addons/shopfloor_delivery_shipment_mobile/__manifest__.py
odoo/addons/shopfloor_delivery_shipment_mobile/i18n/es_AR.po
odoo/addons/shopfloor_delivery_shipment_mobile/i18n/it.po
odoo/addons/shopfloor_delivery_shipment_mobile/i18n/pt_BR.po
odoo/addons/shopfloor_delivery_shipment_mobile/i18n/shopfloor_delivery_shipment_mobile.pot
odoo/addons/shopfloor_delivery_shipment_mobile/readme/CONTRIBUTORS.rst
odoo/addons/shopfloor_delivery_shipment_mobile/readme/DESCRIPTION.rst
odoo/addons/shopfloor_delivery_shipment_mobile/static/description/icon.png
odoo/addons/shopfloor_delivery_shipment_mobile/static/description/index.html
odoo/addons/shopfloor_delivery_shipment_mobile/static/wms/src/demo/demo.delivery_shipment.js
odoo/addons/shopfloor_delivery_shipment_mobile/static/wms/src/scenario/delivery_shipment.js
odoo/addons/shopfloor_delivery_shipment_mobile/templates/assets.xml
odoo14_addon_shopfloor_delivery_shipment_mobile-14.0.1.4.0.dist-info/METADATA
odoo14_addon_shopfloor_delivery_shipment_mobile-14.0.1.4.0.dist-info/WHEEL
odoo14_addon_shopfloor_delivery_shipment_mobile-14.0.1.4.0.dist-info/top_level.txt
odoo14_addon_shopfloor_delivery_shipment_mobile-14.0.1.4.0.dist-info/RECORD
